hdl/master.v




`timescale 1ns/1ns

  module master_bridge(
	input [8:0]apb_write_paddr,apb_read_paddr,
	input [7:0] apb_write_data,PRDATA,         
	input PRESETn,PCLK,READ_WRITE,transfer,PREADY,
	output PSEL1,PSEL2,
	output reg PENABLE,
	output reg [8:0]PADDR,
	output reg PWRITE,
	output reg [7:0]PWDATA,apb_read_data_out,
	  output PSLVERR );  
       // integer i,count;
   
  reg [2:0] state, next_state;

  reg invalid_setup_error,
      setup_error,
      invalid_read_paddr,
      invalid_write_paddr,
      invalid_write_data ;
  
  localparam IDLE = 3'b001, SETUP = 3'b010, ENABLE = 3'b100 ;


  always @(posedge PCLK)
  begin
	if(!PRESETn)
		state <= IDLE;
	else
		state <= next_state; 
  end

  always @(state,transfer,PREADY)

  begin
	if(!PRESETn)
	  next_state = IDLE;
	else
          begin
             PWRITE = ~READ_WRITE;
	     case(state)
                  
		     IDLE: begin 
		              PENABLE =0;

		            if(!transfer)
	        	      next_state = IDLE ;
	                    else
			      next_state = SETUP;
	                   end

	       	SETUP:   begin
			    PENABLE =0;

			    if(READ_WRITE) 
				 //     @(posedge PCLK)
	                       begin   PADDR = apb_read_paddr; end
			    else 
			      begin   
			          //@(posedge PCLK)
                                  PADDR = apb_write_paddr;
				  PWDATA = apb_write_data;  end
			    
			    if(transfer && !PSLVERR)
			      next_state = ENABLE;
		            else
           	              next_state = IDLE;
		           end

	       	ENABLE: 
		     begin if(PSEL1 || PSEL2)
		           PENABLE =1;
			   if(transfer & !PSLVERR)
			   begin
				   if(PREADY)
				   begin
					if(!READ_WRITE)
				         begin
				          
					   next_state = SETUP; end
					else 
					   begin
					   next_state = SETUP; 
				          	   
                                           apb_read_data_out = PRDATA; 
					   end
			            end
				    else next_state = ENABLE;
		              end
		             else next_state = IDLE;
			 end
			   
		        /* if(transfer && !PREADY && READ_WRITE)
                             begin
                              //   repeat(3) @(posedge PCLK)  
                		// begin
			          //  if(!transfer)
                                    //  next_state = IDLE;
		                    //else 
                                      // begin
                                        //if(PREADY) begin
                                          //  next_state = SETUP;
                                            //apb_read_data_out = PRDATA; end
                                        //else
                                            next_state = ENABLE;
				       //end 
                                end
		            end

                       else if(transfer && PREADY && READ_WRITE )
                                 begin
			           apb_read_data_out = PRDATA; 
                                   next_state = SETUP; 
			         end
                                                    
		       else if(transfer && !PREADY && !READ_WRITE)
                                   begin
                                   //   repeat(3) @(posedge PCLK)                                          
			             //   begin
			               // if(!transfer)
                                    //     next_state = IDLE;
				      //  else begin
				        //  if(PREADY) 
					  //   next_state = SETUP;
				          //else
						  next_state = ENABLE;
				         end
			             end 
			     end  
					   
                       else if(transfer && PREADY && !READ_WRITE )
			     begin
                                   next_state = SETUP; 
                                  $strobe($time," Enable write operation"); end   */
                             
                       
                                 default: next_state = IDLE; 
               	endcase
             end
          end


 /*     always @(posedge PCLK) 

      begin
	       PWRITE = ~READ_WRITE;

	      case(state)
		      IDLE: begin
			     
			      PENABLE = 0;
		             end

		      SETUP: begin
			      PENABLE =0;
			      if(READ_WRITE) 
				//  @(posedge PCLK)
			          PADDR = apb_read_paddr;
			      else 
			         //@(posedge PCLK)
                                  PADDR = apb_write_paddr;
				  PWDATA = apb_write_data;
			     end

		      ENABLE: begin
			      PENABLE =1;
		             end
	      endcase
      end */
     assign {PSEL1,PSEL2} = ((state != IDLE) ? (PADDR[8] ? {1'b0,1'b1} : {1'b1,1'b0}) : 2'd0);

  // PSLVERR LOGIC
  
  always @(*)
       begin
        if(!PRESETn)
	    begin 
	     setup_error =0;
	     invalid_read_paddr = 0;
	     invalid_write_paddr = 0;
	     invalid_write_paddr =0 ;
	    end
        else
	 begin	
          begin
	  if(state == IDLE && next_state == ENABLE)
   		  setup_error = 1;
	  else setup_error = 0;
          end
          begin
          if((apb_write_data===8'dx) && (!READ_WRITE) && (state==SETUP || state==ENABLE))
		  invalid_write_data =1;
	  else invalid_write_data = 0;
          end
          begin
	  if((apb_read_paddr===9'dx) && READ_WRITE && (state==SETUP || state==ENABLE))
		  invalid_read_paddr = 1;
	  else  invalid_read_paddr = 0;
          end
          begin
          if((apb_write_paddr===9'dx) && (!READ_WRITE) && (state==SETUP || state==ENABLE))
		  invalid_write_paddr =1;
          else invalid_write_paddr =0;
          end
          begin
	  if(state == SETUP)
            begin
                 if(PWRITE)
                      begin
                         if(PADDR==apb_write_paddr && PWDATA==apb_write_data)
                              setup_error=1'b0;
                         else
                               setup_error=1'b1;
                       end
                 else 
                       begin
                          if (PADDR==apb_read_paddr)
                                 setup_error=1'b0;
                          else
                                 setup_error=1'b1;
                       end    
              end 
          
         else setup_error=1'b0;
         end 
       end
       invalid_setup_error = setup_error ||  invalid_read_paddr || invalid_write_data || invalid_write_paddr  ;
     end 

   assign PSLVERR =  invalid_setup_error ;

	 

 endmodule

tests/wrappers/apb_test.v
`timescale 1ns/1ns

 module master_test(
	input [8:0]apb_write_paddr,apb_read_paddr,
	input [7:0] apb_write_data,PRDATA,         
	input PRESETn,READ_WRITE,transfer,PREADY,
	output reg PCLK,
	output PSEL1,PSEL2,
	output reg PENABLE,
	output reg [8:0]PADDR,
	output reg PWRITE,
	output reg [7:0]PWDATA,apb_read_data_out,
	output PSLVERR ); 

master_bridge mas(
	.apb_write_paddr(apb_write_paddr),
	.apb_read_paddr(apb_read_paddr),
	.apb_write_data(apb_write_data),
	.PRDATA(PRDATA),
	.PRESETn(PRESETn),
	.PCLK(PCLK),
	.READ_WRITE(READ_WRITE),
	.transfer(transfer),
	.PREADY(PREADY),
	.PSEL1(PSEL1),
	.PSEL2(PSEL2),
	.PENABLE(PENABLE),
	.PADDR(PADDR),
	.PWRITE(PWRITE),
	.PWDATA(PWDATA),
	.apb_read_data_out(apb_read_data_out),
	.PSLVERR(PSLVERR)
);
initial begin
	$dumpfile("master.vcd");
	$dumpvars;
	PCLK=0;
	forever begin
            #1 PCLK=~PCLK;
        end
end
endmodule

tests/master.vcd
$date
	Sun Jul  2 01:43:15 2023
$end
$version
	Icarus Verilog
$end
$timescale
	1ps
$end
$scope module master_test $end
$var wire 8 ! PRDATA [7:0] $end
$var wire 1 " PREADY $end
$var wire 1 # PRESETn $end
$var wire 1 $ READ_WRITE $end
$var wire 9 % apb_read_paddr [8:0] $end
$var wire 8 & apb_write_data [7:0] $end
$var wire 9 ' apb_write_paddr [8:0] $end
$var wire 1 ( transfer $end
$var wire 8 ) apb_read_data_out [7:0] $end
$var wire 1 * PWRITE $end
$var wire 8 + PWDATA [7:0] $end
$var wire 1 , PSLVERR $end
$var wire 1 - PSEL2 $end
$var wire 1 . PSEL1 $end
$var wire 1 / PENABLE $end
$var wire 9 0 PADDR [8:0] $end
$var reg 1 1 PCLK $end
$scope module mas $end
$var wire 1 1 PCLK $end
$var wire 8 2 PRDATA [7:0] $end
$var wire 1 " PREADY $end
$var wire 1 # PRESETn $end
$var wire 1 , PSLVERR $end
$var wire 1 $ READ_WRITE $end
$var wire 9 3 apb_read_paddr [8:0] $end
$var wire 8 4 apb_write_data [7:0] $end
$var wire 9 5 apb_write_paddr [8:0] $end
$var wire 1 ( transfer $end
$var wire 1 - PSEL2 $end
$var wire 1 . PSEL1 $end
$var reg 9 6 PADDR [8:0] $end
$var reg 1 / PENABLE $end
$var reg 8 7 PWDATA [7:0] $end
$var reg 1 * PWRITE $end
$var reg 8 8 apb_read_data_out [7:0] $end
$var reg 1 9 invalid_read_paddr $end
$var reg 1 : invalid_setup_error $end
$var reg 1 ; invalid_write_data $end
$var reg 1 < invalid_write_paddr $end
$var reg 3 = next_state [2:0] $end
$var reg 1 > setup_error $end
$var reg 3 ? state [2:0] $end
$upscope $end
$upscope $end
$enddefinitions $end
#0
$dumpvars
bx ?
0>
b1 =
0<
0;
0:
09
bx 8
bx 7
bx 6
bz 5
bz 4
bz 3
bz 2
01
bx 0
x/
x.
x-
0,
bx +
x*
bx )
z(
bz '
bz &
bz %
z$
1#
z"
bz !
$end
#1000
0#
0-
0.
b10 =
0/
b1 ?
11
#2000
01
#3000
b1010 '
b1010 5
1#
11
#4000
01
#5000
b11100 &
b11100 4
0-
1.
1,
1:
1>
b1 =
bz +
bz 7
b1010 0
b1010 6
b10 ?
11
#6000
01
#7000
1*
0$
1(
0"
0.
0,
0:
0>
b10 =
b1 ?
11
#8000
01
#9000
1.
b100 =
b11100 +
b11100 7
b10 ?
11
#10000
01
#11000
b10 =
1"
b11101 &
b11101 4
1/
b100 ?
11
#12000
b1011 '
b1011 5
01
#13000
0"
b100 =
b11101 +
b11101 7
b1011 0
b1011 6
0/
b10 ?
11
#14000
01
#15000
b10 =
1"
b11110 &
b11110 4
1/
b100 ?
11
#16000
b1100 '
b1100 5
01
#17000
0"
b100 =
b11110 +
b11110 7
b1100 0
b1100 6
0/
b10 ?
11
#18000
01
#19000
b10 =
1"
b11111 &
b11111 4
1/
b100 ?
11
#20000
b1101 '
b1101 5
01
#21000
0"
b100 =
b11111 +
b11111 7
b1101 0
b1101 6
0/
b10 ?
11
#22000
01
#23000
b10 =
1"
b100000 &
b100000 4
1/
b100 ?
11
#24000
b1110 '
b1110 5
01
#25000
0"
b100 =
b100000 +
b100000 7
b1110 0
b1110 6
0/
b10 ?
11
#26000
01
#27000
b10 =
1"
b100001 &
b100001 4
1/
b100 ?
11
#28000
b1111 '
b1111 5
01
#29000
0"
b100 =
b100001 +
b100001 7
b1111 0
b1111 6
0/
b10 ?
11
#30000
01
#31000
b10 =
1"
b100010 &
b100010 4
1/
b100 ?
11
#32000
b10000 '
b10000 5
01
#33000
0"
b100 =
b100010 +
b100010 7
b10000 0
b10000 6
0/
b10 ?
11
#34000
01
#35000
b10 =
1"
b100011 &
b100011 4
1/
b100 ?
11
#36000
b10001 '
b10001 5
01
#37000
0"
b100 =
b100011 +
b100011 7
b10001 0
b10001 6
0/
b10 ?
11
#38000
01
#39000
b10 =
1"
b100100 &
b100100 4
1/
b100 ?
11
#40000
b10010 '
b10010 5
01
#41000
0"
b100 =
b100100 +
b100100 7
b10010 0
b10010 6
0/
b10 ?
11
#42000
01
#43000
b10 =
1"
b100101 &
b100101 4
1/
b100 ?
11
#44000
b10011 '
b10011 5
01
#45000
0"
b100 =
b100101 +
b100101 7
b10011 0
b10011 6
0/
b10 ?
11
#46000
01
#47000
b10 =
1"
1/
b100 ?
11
#48000
01
#49000
0"
b100 =
0/
b10 ?
11
#50000
01
#51000
1/
b100 ?
11
#51001
0#
#52000
01
#53000
b1100101 %
b1100101 3
1#
0.
b1 =
b1 ?
11
#54000
01
#55000
b10 =
0/
0*
1"
b11100 !
b11100 2
1$
11
#56000
01
#57000
0"
1.
b100 =
b1100101 0
b1100101 6
b10 ?
11
#58000
01
#59000
b11101 )
b11101 8
b10 =
1"
b11101 !
b11101 2
1/
b100 ?
11
#60000
01
#61000
0"
b100 =
0/
b10 ?
11
#62000
01
#63000
b11110 )
b11110 8
b10 =
1"
b11110 !
b11110 2
1/
b100 ?
11
#64000
01
#65000
0"
b100 =
0/
b10 ?
11
#66000
01
#67000
b11111 )
b11111 8
b10 =
1"
b11111 !
b11111 2
1/
b100 ?
11
#68000
01
#69000
0"
b100 =
0/
b10 ?
11
#70000
01
#71000
b100000 )
b100000 8
b10 =
1"
b100000 !
b100000 2
1/
b100 ?
11
#72000
01
#73000
0"
b100 =
0/
b10 ?
11
#74000
01
#75000
b100001 )
b100001 8
b10 =
1"
b100001 !
b100001 2
1/
b100 ?
11
#76000
01
#77000
0"
b100 =
0/
b10 ?
11
#78000
01
#79000
b100010 )
b100010 8
b10 =
1"
b100010 !
b100010 2
1/
b100 ?
11
#80000
01
#81000
0"
b100 =
0/
b10 ?
11
#82000
01
#83000
b100011 )
b100011 8
b10 =
1"
b100011 !
b100011 2
1/
b100 ?
11
#84000
01
#85000
0"
b100 =
0/
b10 ?
11
#86000
01
#87000
b100100 )
b100100 8
b10 =
1"
b100100 !
b100100 2
1/
b100 ?
11
#88000
01
#89000
0"
b100 =
0/
b10 ?
11
#90000
01
#91000
b100101 )
b100101 8
b10 =
1"
b100101 !
b100101 2
1/
b100 ?
11
#92000
01
#93000
0"
b100 =
0/
b10 ?
11
#94000
01
#95000
b10 =
1"
1/
b100 ?
11
#96000
01
#97000
b100 =
0/
b10 ?
11
